dhk/csv2xlsx/__init__.py
dhk/csv2xlsx/cli.py
dhk/csv2xlsx/csv2xlsx.py
dhk_csv2xlsx-2.0.0.data/scripts/csv2xlsx
dhk_csv2xlsx-2.0.0.dist-info/METADATA
dhk_csv2xlsx-2.0.0.dist-info/WHEEL
dhk_csv2xlsx-2.0.0.dist-info/namespace_packages.txt
dhk_csv2xlsx-2.0.0.dist-info/top_level.txt
dhk_csv2xlsx-2.0.0.dist-info/zip-safe
dhk_csv2xlsx-2.0.0.dist-info/RECORD
