Metadata-Version: 2.4
Name: dhk.csv2xlsx
Version: 2.0.0
Summary: Read a CSV file and write an XLSX file with optional formatting.
Home-page: https://github.com/DavidKiesel/python-csv2xlsx
Author: David Harris Kiesel
Author-email: david.sw@suddenthought.net
Maintainer: David Harris Kiesel
Maintainer-email: david.sw@suddenthought.net
License: MIT
Project-URL: Homepage, https://github.com/DavidKiesel/python-csv2xlsx
Classifier: Development Status :: 3 - Alpha
Classifier: Environment :: Console
Classifier: Intended Audience :: Developers
Classifier: Programming Language :: Python
Classifier: Programming Language :: Python :: 3
Classifier: Programming Language :: Python :: 3.9
Classifier: Programming Language :: Python :: 3.10
Classifier: Programming Language :: Python :: 3.11
Classifier: Programming Language :: Python :: 3.12
Classifier: Programming Language :: Python :: 3.13
Requires-Python: >=3.9
Requires-Dist: XlsxWriter==3.2.3
Dynamic: author
Dynamic: author-email
Dynamic: classifier
Dynamic: description
Dynamic: description-content-type
Dynamic: home-page
Dynamic: keywords
Dynamic: license
Dynamic: maintainer
Dynamic: maintainer-email
Dynamic: project-url
Dynamic: requires-dist
Dynamic: requires-python
Dynamic: summary
